LICENSE
README.md
setup.py
lomas_client/__init__.py
lomas_client/client.py
lomas_client/constants.py
lomas_client/http_client.py
lomas_client/utils.py
lomas_client.egg-info/PKG-INFO
lomas_client.egg-info/SOURCES.txt
lomas_client.egg-info/dependency_links.txt
lomas_client.egg-info/requires.txt
lomas_client.egg-info/top_level.txt
lomas_client/libraries/__init__.py
lomas_client/libraries/diffprivlib.py
lomas_client/libraries/opendp.py
lomas_client/libraries/smartnoise_sql.py
lomas_client/libraries/smartnoise_synth.py