Metadata-Version: 2.2
Name: lomas_client
Version: 0.4.1
Summary: A client to interact with the Lomas server.
Home-page: https://github.com/dscc-admin/lomas/
Author: Data Science Competence Center, Swiss Federal Statistical Office
Author-email: dscc@bfs.admin.ch
License: MIT
Keywords: differential privacy,DP,diffprivlib,logger,opendp,privacy,smartnoise-sql,smartnoise-synth
Classifier: Development Status :: 4 - Beta
Classifier: Intended Audience :: Developers
Classifier: Intended Audience :: Science/Research
Classifier: License :: OSI Approved :: MIT License
Classifier: Natural Language :: English
Classifier: Programming Language :: Python :: 3.11
Classifier: Programming Language :: Python :: 3.12
Classifier: Topic :: Software Development :: Libraries
Classifier: Topic :: Software Development :: Libraries :: Python Modules
Classifier: Topic :: Scientific/Engineering
Classifier: Topic :: Security
Requires-Python: >=3.11, <3.13
License-File: LICENSE
Requires-Dist: lomas-core==0.4.1
Requires-Dist: opentelemetry-instrumentation-requests==0.50b0
Requires-Dist: requests==2.32.0
Dynamic: author
Dynamic: author-email
Dynamic: classifier
Dynamic: description
Dynamic: description-content-type
Dynamic: home-page
Dynamic: keywords
Dynamic: license
Dynamic: requires-dist
Dynamic: requires-python
Dynamic: summary
